{"----\u5bfc\u822a\u5206\u7c7b----":"","nav":{"tank":" R\u00e9servoirs ","puzzle":" Nest ","physics":" physique ","parking":" Disponible ","ninja":" Ninja ","multiplayer":" Multijoueur ","maze":" Maze ","matching":" match ","logic":" Logique ","life":" Mode de vie ","funny":" Funny ","skill":" Comp\u00e9tences ","dress-up":" robe ","cooking":" Cuisine ","classic":" Classic ","card":" Carte brand ","board":" Echecs ","billiards":" billard ","bike":" Cyclisme ","basketball":" Basket ","action":" action ","racing":" Racing ","car":" Automobile ","hot":" Hot ","more":" PLUS ","game":" Jeux ","games":" Liste ","comment":" Les commentaires jeu ","related_games":" Jeux similaires ","popular_games":" Jeux Hot ","skip_ad":" saut Guo AD ","christmas":" No\u00ebl ","mario":" Mario ","girls":" Fille ","spiderman":" Spiderman ","tag":" tag ","tag_list":" liste de tag ","categories":" category ","merry_christmas":" Merry Christmas ","home":" Accueil ","played":" Jou\u00e9 ","favorite":" pr\u00e9f\u00e9r\u00e9e ","html5":" HTML5 ","adventure":" Aventure ","aircraft":" avions ","animal":" Animaux ","arcade":" Arcade ","baby":" Baby ","balance":" Balance ","ball":" Bal ","balloons":" Ballons ","bananas":" banane ","batman":" Batman ","bicycle":" Cyclisme ","cake":" G\u00e2teaux ","candy":" candy ","fighting":" combats ","football":" Football ","free":" libre ","fruit":" Fruit ","love":" Amour ","memory":" M\u00e9moire ","motorcycle":" Moto ","numbers":" num\u00e9rique ","online":" ligne ","panda":" panda ","romance":" Romantique ","sexy":" Sexy ","shooting":" tournage ","sports":" Sports ","stick":" bar ","strategy":" Politiques ","surf":" Surfers ","tractor":" tracteur ","tower_defense":" Tower Defense ","train":" voiture ","truck":" Camion ","violence":" violence ","war":" Guerre ","zombies":" Zombies ","top_collections":" populaire ","game_intro":" Description du jeu ","screen_shot":" screenshots ","top_games":" Jeux Hot ","controls":" Contr\u00f4le ","description":" Introduction ","barbie":" Barbie","top_games":"meilleurs jeux"}}