{"----\u5bfc\u822a\u5206\u7c7b----":"","nav":{"tank":" Zbiorniki","puzzle":"Nest","physics":"fizyczne","parking":"Dost\u0119pne","ninja":"Ninja","multiplayer":"Multiplayer","maze":"Labirynt","matching":"Mecz","logic":"logika","life":"Styl \u017cycia","funny":"\u015amieszne","skill":"Umiej\u0119tno\u015bci","dress-up":"sukienka","cooking":"Gotowanie","classic":"Klasyczny","card":"karty Marka","board":"Szachy","billiards":"bilard","bike":"Kolarstwo","basketball":"Koszyk\u00f3wka","action":"Akcja","racing":"Wy\u015bcigi","car":"Motoryzacja","hot":"Hot","more":"WI\u0118CEJ","game":"Gry","games":"","comment":" Lista gier Recenzje","related_games":"Podobne Gry","popular_games":"Hot Games","skip_ad":"skok Guo AD","christmas":"Bo\u017ce Narodzenie","mario":"Mario","girls":"Dziewczyna","spiderman":"spiderman","tag":"tag","tag_list":"Lista tag","categories":"category","merry_christmas":"Weso\u0142ych \u015awi\u0105t","home":"Strona g\u0142\u00f3wna","played":"Gry","favorite":"ulubiona","html5":"HTML5","adventure":"Przygodowe","aircraft":"Samoloty","animal":"Zwierz\u0119ta","arcade":"Arcade","baby":"Dziecko","balance":"Balans","ball":"Pi\u0142ka","balloons":"Balony","bananas":"banan","batman":"Batman","bicycle":"Kolarstwo","cake":"Ciasta","candy":"cukierki","fighting":"walki","football":"Pi\u0142ka no\u017cna","free":"wolne","fruit":"Owoce","love":"Mi\u0142o\u015b\u0107","memory":"Pami\u0119\u0107","motorcycle":"Motocykle","numbers":"Cyfrowe","online":"Online","panda":"panda","romance":"Romantyczny","sexy":"Sexy","shooting":"Strzelanie","sports":"Sport","stick":"bar","strategy":"Polityka","surf":"Surfers","tractor":"Traktor","tower_defense":"Tower Defense","train":"samoch\u00f3d","truck":"Ci\u0119\u017car\u00f3wka","violence":"Przemoc","war":"Wojna","zombies":"Zombies","top_collections":"Popularny","game_intro":"opis gry","screen_shot":"screeny","top_games":"Hot Games","controls":"sterowania","description":"Wprowadzenie","barbie":"Barbie","top_games":"lista gier"}}